fpl_mcp/__init__.py
fpl_mcp/__main__.py
fpl_mcp/cli.py
fpl_mcp/config.py
fpl_mcp/fpl/__init__.py
fpl_mcp/fpl/api.py
fpl_mcp/fpl/auth_manager.py
fpl_mcp/fpl/cache.py
fpl_mcp/fpl/rate_limiter.py
fpl_mcp/fpl/resources/__init__.py
fpl_mcp/fpl/resources/fixtures.py
fpl_mcp/fpl/resources/gameweeks.py
fpl_mcp/fpl/resources/players.py
fpl_mcp/fpl/resources/teams.py
fpl_mcp/fpl/tools/__init__.py
fpl_mcp/fpl/tools/comparisons.py
fpl_mcp/fpl/tools/leagues.py
fpl_mcp/fpl/tools/managers.py
fpl_mcp/fpl/tools/players.py
fpl_mcp/fpl/tools/simplified_decision.py
fpl_mcp/fpl/tools/team.py
fpl_mcp/fpl/utils/__init__.py
fpl_mcp/fpl/utils/position_utils.py
fpl_mcp/schemas/static_schema.json
mseep_fpl_mcp-0.1.6.dist-info/licenses/LICENSE
mseep_fpl_mcp-0.1.6.dist-info/METADATA
mseep_fpl_mcp-0.1.6.dist-info/WHEEL
mseep_fpl_mcp-0.1.6.dist-info/entry_points.txt
mseep_fpl_mcp-0.1.6.dist-info/top_level.txt
mseep_fpl_mcp-0.1.6.dist-info/RECORD
